hexdumper/Controller.py
hexdumper/__init__.py
hexdumper/__main__.py
hexdumper-2.0.2.dist-info/LICENSE.md
hexdumper-2.0.2.dist-info/METADATA
hexdumper-2.0.2.dist-info/WHEEL
hexdumper-2.0.2.dist-info/entry_points.txt
hexdumper-2.0.2.dist-info/top_level.txt
hexdumper-2.0.2.dist-info/RECORD
