Metadata-Version: 2.1
Name: hexdumper
Version: 2.0.2
Summary: Creates the hexdump of a selected file
Home-page: https://github.com/5f0ne/hexdump
Author: 5f0
License: MIT
Classifier: Operating System :: OS Independent 
Classifier: Programming Language :: Python :: 3 
Classifier: License :: OSI Approved :: MIT License 
License-File: LICENSE.md
Requires-Dist: hash-calc (==1.1.0)
Requires-Dist: hexlib (==2.0.3)
